generic_struct/__init__.py
generic_struct/parsers/DelimitedBuffer.py
generic_struct/parsers/DelimitedList.py
generic_struct/parsers/DynamicSizeBuffer.py
generic_struct/parsers/DynamicSizeList.py
generic_struct/parsers/StaticField.py
generic_struct/parsers/StaticSizeBuffer.py
generic_struct/parsers/StaticSizeList.py
generic_struct/parsers/Union.py
generic_struct/parsers/__init__.py
generic_struct/structs/Flags.py
generic_struct/structs/GenericStruct.py
generic_struct/structs/__init__.py
generic_struct-1.0.3.dist-info/LICENSE
generic_struct-1.0.3.dist-info/METADATA
generic_struct-1.0.3.dist-info/WHEEL
generic_struct-1.0.3.dist-info/top_level.txt
generic_struct-1.0.3.dist-info/RECORD
