Metadata-Version: 2.1
Name: generic-struct
Version: 1.0.3
Summary: A simple package to simplify conversion between binary data and python objects
Home-page: UNKNOWN
Author: Ori Pardo
Author-email: pardooori@gmail.com
License: UNKNOWN
Platform: UNKNOWN
Classifier: Programming Language :: Python :: 3
Classifier: Operating System :: OS Independent
Classifier: Intended Audience :: Developers
Requires-Python: >=3.6
